{"id":"4912DE3D-156B-4B0C-8333-CAB491A757F5","validationEntity":{"analysedDataType":"auto","dataResult":{}},"modelEntity":{"createdDate":"2021-04-10T21:36:57Z","id":"679D3D33-AC81-4054-83F5-D4560433F1B2","experimentID":"4912DE3D-156B-4B0C-8333-CAB491A757F5","title":"","modifiedDate":"2021-04-10T21:36:57Z","preferredFilename":"","version":"1.0","modelURL":"Models\/BetterRest%201.mlmodel"},"version":"1.0","settingEntity":{"augmentations":[],"suggestedColumns":["wake","estimatedSleep","coffee","actualSleep"],"targetColumn":"actualSleep","seedType":"default","transferLearningEmbeddingType":"dynamic","featureNames":["wake","estimatedSleep","coffee"],"algorithmType":"maxEnt","harVideoAugmentations":0,"taskType":"generalRegresor","suggestedColumnValues":["31.500, 32.400, 26.100, 40.500, 19.800, 27.000, 20.700, 21.600, 41.400, 34.200, 21.600, 78.300, 32.400, 28.800, 18.900, 18.000, 28.800, 18.000, 7.200, 35.100, 24.300, 35.100, 34.200, 27.900, 30.600, 69.300, 35.100, 34.200, 34.200, 23.400","9,00, 5,00, 6,50, 8,75, 6,00, 7,50, 9,25, 6,00, 9,25, 6,75, 5,25, 9,25, 10,00, 8,75, 8,25, 6,25, 10,00, 6,25, 10,00, 9,50, 5,00, 7,50, 6,25, 8,00, 8,00, 6,50, 8,00, 10,00, 8,25, 8,00","6, 2, 10, 4, 3, 1, 1, 3, 5, 8, 3, 8, 2, 3, 1, 2, 3, 2, 1, 4, 2, 1, 1, 4, 3, 7, 4, 4, 1, 3","38.230, 20.180, 31.989, 35.258, 24.487, 28.300, 34.548, 24.557, 37.836, 31.340, 21.874, 40.405, 38.076, 34.265, 30.936, 24.665, 39.007, 24.578, 37.267, 37.878, 20.220, 28.400, 23.882, 32.427, 31.699, 29.670, 32.789, 39.792, 30.935, 31.701"],"suggestedColumnTypes":["Int","Double","Int","Int"],"generalRegressorType":{"randomForest":{"rowSubsample":0.80000000000000004,"columnSubsample":0.80000000000000004,"minLossReduction":0,"minChildWeight":0.10000000000000001,"maxDepth":6}},"styleTransferAlgorithmType":"image","iterationCount":10},"state":"trained","trainingEntity":{"finishTime":"2021-04-10T21:42:17Z","recipeTrainingResults":{"generalRegressor":{"maximumError":6095.58203125,"rootMeanSquaredError":1593.8159007203099}},"dataResult":{"itemsCount":10000,"dataURL":"file:\/\/\/Users\/ronaldogomes\/Desktop\/Another%20Projects\/HackingWithSwift-main\/SwiftUI\/project4-files\/BetterRest.csv","columns":["wake","estimatedSleep","coffee","actualSleep"],"columnTypes":["Int","Double","Int","Int"],"analysis":{"summary":{"sampleCount":10000,"canUseValidation":1},"issues":[{"description":"Data has 10000 rows","severity":"info"}],"regressorAnalysis":{"targetRange":[19216,45224]}},"dataSourceID":"9B496A9C-5A24-46A0-A0E5-FFBBDF4A58E1","columnValues":["31.500, 32.400, 26.100, 40.500, 19.800, 27.000, 20.700, 21.600, 41.400, 34.200, 21.600, 78.300, 32.400, 28.800, 18.900, 18.000, 28.800, 18.000, 7.200, 35.100, 24.300, 35.100, 34.200, 27.900, 30.600, 69.300, 35.100, 34.200, 34.200, 23.400","9,00, 5,00, 6,50, 8,75, 6,00, 7,50, 9,25, 6,00, 9,25, 6,75, 5,25, 9,25, 10,00, 8,75, 8,25, 6,25, 10,00, 6,25, 10,00, 9,50, 5,00, 7,50, 6,25, 8,00, 8,00, 6,50, 8,00, 10,00, 8,25, 8,00","6, 2, 10, 4, 3, 1, 1, 3, 5, 8, 3, 8, 2, 3, 1, 2, 3, 2, 1, 4, 2, 1, 1, 4, 3, 7, 4, 4, 1, 3","38.230, 20.180, 31.989, 35.258, 24.487, 28.300, 34.548, 24.557, 37.836, 31.340, 21.874, 40.405, 38.076, 34.265, 30.936, 24.665, 39.007, 24.578, 37.267, 37.878, 20.220, 28.400, 23.882, 32.427, 31.699, 29.670, 32.789, 39.792, 30.935, 31.701"],"targetRange":[19216,45224]},"dataURL":"file:\/\/\/Users\/ronaldogomes\/Desktop\/Another%20Projects\/HackingWithSwift-main\/SwiftUI\/project4-files\/BetterRest.csv","featureExtractionCheckpointMayBeAvailable":false,"recipeValidationResults":{"generalRegressor":{"maximumError":5429.58203125,"rootMeanSquaredError":1590.5803405847591}},"progress":[],"trainingAccuracy":1593.8159007203099,"checkpointMetrics":{},"analysedDataType":"datasource","dataSourceID":"9B496A9C-5A24-46A0-A0E5-FFBBDF4A58E1","snapshottableCheckpoints":{},"validationAccuracy":1590.5803405847591,"startTime":"2021-04-10T21:42:16Z"},"createdDate":"2021-04-10T21:36:57Z","snapshotRole":{"withoutSnapshots":0},"evaluationEntities":[],"activityEntities":["trainingDataAdded",[{"id":"6966BC9D-CB87-4A4C-B9BC-C53AB866A6E8","title":"Training Data Added","createdDate":"2021-04-10T21:38:37Z","event":"trainingDataAdded","subtitle":"BetterRest.csv"}],"trainingFinished",[{"id":"B79E5D0C-6B48-4D5B-B244-920274D2650E","title":"Training Completed","createdDate":"2021-04-10T21:42:17Z","event":"trainingFinished","subtitle":"10 iterations"}],"experimentCreated",[{"id":"152C67EB-2B26-45B1-A063-2D704E42CD73","title":"Model Source Created","createdDate":"2021-04-10T21:36:57Z","event":"experimentCreated","subtitle":"BetterRest 1"}],"trainingStarted",[{"id":"07EDA1C5-874F-4FE0-B0EA-30928C2494A4","title":"Training Started","createdDate":"2021-04-10T21:42:16Z","event":"trainingStarted","subtitle":"10 iterations"}]],"title":"BetterRest 1","evaluationEntity":{"id":"72ed8609-a411-40c6-9138-9cb7da042ad9","analysedDataType":"none","dataResult":{}},"evaluationState":"uninitialized","contentDataResult":{},"modifiedDate":"2021-04-10T21:42:17Z","preferredFilename":"BetterRest 1"}