{"id":"FAEBF2B8-1F83-41C1-B087-0AE0E7CA07F4","validationEntity":{"analysedDataType":"auto","dataResult":{}},"modelEntity":{"createdDate":"2020-10-11T00:08:20Z","id":"E0A6F700-8754-4234-9DF1-D1DC293AAC7E","experimentID":"FAEBF2B8-1F83-41C1-B087-0AE0E7CA07F4","title":"","modifiedDate":"2020-10-11T00:08:20Z","preferredFilename":"","version":"1.0"},"version":"1.0","settingEntity":{"taskType":"imageClassifier","styleTransferAlgorithmType":"image","augmentations":[],"harVideoAugmentations":0,"transferLearningEmbeddingType":"dynamic","algorithmType":"maxEnt","seedType":"default","featureNames":[]},"state":"uninitialized","trainingEntity":{"checkpointMetrics":{},"dataResult":{},"snapshottableCheckpoints":{},"analysedDataType":"choose","featureExtractionCheckpointMayBeAvailable":false,"progress":[]},"createdDate":"2020-10-11T00:08:20Z","snapshotRole":{"withoutSnapshots":0},"evaluationEntities":[],"activityEntities":["experimentCreated",[{"id":"5B04A595-1AB1-4A36-8F50-5B1CABA1F960","title":"Model Source Created","createdDate":"2020-10-11T00:08:20Z","event":"experimentCreated","subtitle":"MyFisrtImageClassifier 1"}]],"title":"MyFisrtImageClassifier 1","evaluationEntity":{"id":"941463b0-b242-4be7-ac2b-f4dbeac400de","analysedDataType":"none","dataResult":{}},"evaluationState":"uninitialized","contentDataResult":{},"modifiedDate":"2020-10-11T00:08:20Z","preferredFilename":"MyFisrtImageClassifier 1"}